qrcode-stubs/LUT.pyi
qrcode-stubs/METADATA.toml
qrcode-stubs/__init__.pyi
qrcode-stubs/_types.pyi
qrcode-stubs/base.pyi
qrcode-stubs/console_scripts.pyi
qrcode-stubs/constants.pyi
qrcode-stubs/exceptions.pyi
qrcode-stubs/main.pyi
qrcode-stubs/py.typed
qrcode-stubs/release.pyi
qrcode-stubs/util.pyi
qrcode-stubs/image/__init__.pyi
qrcode-stubs/image/base.pyi
qrcode-stubs/image/pil.pyi
qrcode-stubs/image/pure.pyi
qrcode-stubs/image/styledpil.pyi
qrcode-stubs/image/svg.pyi
qrcode-stubs/image/styles/__init__.pyi
qrcode-stubs/image/styles/colormasks.pyi
qrcode-stubs/image/styles/moduledrawers/__init__.pyi
qrcode-stubs/image/styles/moduledrawers/base.pyi
qrcode-stubs/image/styles/moduledrawers/pil.pyi
qrcode-stubs/image/styles/moduledrawers/svg.pyi
types_qrcode-8.2.0.20250506.dist-info/licenses/LICENSE
types_qrcode-8.2.0.20250506.dist-info/METADATA
types_qrcode-8.2.0.20250506.dist-info/WHEEL
types_qrcode-8.2.0.20250506.dist-info/top_level.txt
types_qrcode-8.2.0.20250506.dist-info/RECORD
